cicd_tempy/__init__.py
cicd_tempy/main.py
cicd_tempy-0.3.0.dist-info/METADATA
cicd_tempy-0.3.0.dist-info/WHEEL
cicd_tempy-0.3.0.dist-info/licenses/LICENSE
cicd_tempy-0.3.0.dist-info/RECORD
