Metadata-Version: 2.4
Name: cicd-tempy
Version: 0.3.0
Summary: Templates for Python projects
Author-email: mo <mohamedmartini1991@gmail.com>
License: MIT License
License-File: LICENSE
Requires-Python: >=3.11
